{
  "header": "MLB News",
  "articles": [
    {
      "id": 45398958,
      "nowId": "1-45398958",
      "contentKey": "45398958-1-21-1",
      "dataSourceIdentifier": "5fbaeaec6d9a0",
      "type": "Recap",
      "headline": "Chapman homers, Harrison pitches five scoreless innings as Giants beat Marlins 2-0",
      "description": "\u2014 Matt Chapman homered, Kyle Harrison pitched five shutout innings and the San Francisco Giants beat the Miami Marlins 2-0 on Friday night.",
      "lastModified": "2025-05-31T02:00:56+00:00",
      "published": "2025-05-31T02:00:57+00:00",
      "images": [
        {
          "type": "stitcher",
          "name": "espn.applewatch.awayhome.1",
          "url": "https://s.espncdn.com/stitcher/sports/baseball/mlb/events/401695756.png?templateId=espn.applewatch.awayhome.1"
        },
        {
          "type": "stitcher",
          "name": "espn.applewatch.homeaway.1",
          "url": "https://s.espncdn.com/stitcher/sports/baseball/mlb/events/401695756.png?templateId=espn.applewatch.homeaway.1"
        },
        {
          "ratio": "16x9",
          "type": "stitcher",
          "name": "espn.all.awayhome.16x9.1",
          "height": 173,
          "width": 308,
          "url": "https://s.espncdn.com/stitcher/sports/baseball/mlb/events/401695756.png?templateId=espn.all.awayhome.16x9.1"
        },
        {
          "ratio": "16x9",
          "type": "stitcher",
          "name": "espn.all.homeaway.16x9.1",
          "height": 173,
          "width": 308,
          "url": "https://s.espncdn.com/stitcher/sports/baseball/mlb/events/401695756.png?templateId=espn.all.homeaway.16x9.1"
        },
        {
          "ratio": "1x1",
          "type": "stitcher",
          "name": "espn.all.awayhome.1x1.1",
          "height": 308,
          "width": 308,
          "url": "https://s.espncdn.com/stitcher/sports/baseball/mlb/events/401695756.png?templateId=espn.all.awayhome.1x1.1"
        },
        {
          "ratio": "1x1",
          "type": "stitcher",
          "name": "espn.all.homeaway.1x1.1",
          "height": 308,
          "width": 308,
          "url": "https://s.espncdn.com/stitcher/sports/baseball/mlb/events/401695756.png?templateId=espn.all.homeaway.1x1.1"
        },
        {
          "ratio": "5x2",
          "type": "stitcher",
          "name": "espn.all.awayhome.5x2.1",
          "height": 124,
          "width": 308,
          "url": "https://s.espncdn.com/stitcher/sports/baseball/mlb/events/401695756.png?templateId=espn.all.awayhome.5x2.1"
        },
        {
          "ratio": "5x2",
          "type": "stitcher",
          "name": "espn.all.homeaway.5x2.1",
          "height": 124,
          "width": 308,
          "url": "https://s.espncdn.com/stitcher/sports/baseball/mlb/events/401695756.png?templateId=espn.all.homeaway.5x2.1"
        },
        {
          "ratio": "16x9",
          "type": "stitcher",
          "name": "espn.all.awayhome.16x9.2",
          "height": 353,
          "width": 628,
          "url": "https://s.espncdn.com/stitcher/sports/baseball/mlb/events/401695756.png?templateId=espn.all.awayhome.16x9.2"
        },
        {
          "ratio": "16x9",
          "type": "stitcher",
          "name": "espn.all.homeaway.16x9.2",
          "height": 353,
          "width": 628,
          "url": "https://s.espncdn.com/stitcher/sports/baseball/mlb/events/401695756.png?templateId=espn.all.homeaway.16x9.2"
        },
        {
          "ratio": "5x2",
          "type": "stitcher",
          "name": "espn.all.awayhome.5x2.2",
          "height": 251,
          "width": 628,
          "url": "https://s.espncdn.com/stitcher/sports/baseball/mlb/events/401695756.png?templateId=espn.all.awayhome.5x2.2"
        },
        {
          "ratio": "5x2",
          "type": "stitcher",
          "name": "espn.all.homeaway.5x2.2",
          "height": 251,
          "width": 628,
          "url": "https://s.espncdn.com/stitcher/sports/baseball/mlb/events/401695756.png?templateId=espn.all.homeaway.5x2.2"
        },
        {
          "type": "Media",
          "name": "Matt Chapman doubles Giants' lead with 10th HR of season",
          "height": 324,
          "width": 576,
          "url": "https://a.espncdn.com/media/motion/2025/0530/ss_20250530_215634337_2870764/ss_20250530_215634337_2870764.jpg",
          "caption": "Matt Chapman sends one 420 feet to give the Giants a 2-0 lead over the Marlins."
        }
      ],
      "categories": [
        {
          "type": "team",
          "guid": "74909d10-eacb-1376-ef1e-d0f37d7c67ca",
          "id": 501,
          "description": "Miami Marlins",
          "sportId": 10,
          "uid": "s:1~l:10~t:28",
          "teamId": 28,
          "team": {
            "id": 28,
            "description": "Miami Marlins",
            "links": {
              "web": {
                "teams": {
                  "href": "https://www.espn.com/mlb/team/_/name/mia/miami-marlins"
                }
              },
              "mobile": {
                "teams": {
                  "href": "https://www.espn.com/mlb/team/_/name/mia/miami-marlins"
                }
              }
            }
          }
        },
        {
          "type": "league",
          "guid": "b38f959b-7865-31ac-8841-b88355519e10",
          "id": 80311,
          "description": "MLB",
          "sportId": 10,
          "uid": "s:1~l:10",
          "leagueId": 10,
          "league": {
            "id": 10,
            "description": "MLB",
            "abbreviation": "MLB",
            "links": {
              "web": {
                "leagues": {
                  "href": "https://www.espn.com/mlb/"
                }
              },
              "mobile": {
                "leagues": {
                  "href": "https://www.espn.com/mlb/"
                }
              }
            }
          }
        },
        {
          "type": "team",
          "guid": "e072b79c-4fa1-3a55-bdcd-4d7d9734d79b",
          "id": 751,
          "description": "San Francisco Giants",
          "sportId": 10,
          "uid": "s:1~l:10~t:26",
          "teamId": 26,
          "team": {
            "id": 26,
            "description": "San Francisco Giants",
            "links": {
              "web": {
                "teams": {
                  "href": "https://www.espn.com/mlb/team/_/name/sf/san-francisco-giants"
                }
              },
              "mobile": {
                "teams": {
                  "href": "https://www.espn.com/mlb/team/_/name/sf/san-francisco-giants"
                }
              }
            }
          }
        },
        {
          "type": "guid",
          "guid": "3bbbdbc9-bc88-3d07-849d-37f0acdab0e7"
        },
        {
          "type": "guid",
          "guid": "74909d10-eacb-1376-ef1e-d0f37d7c67ca"
        },
        {
          "type": "guid",
          "guid": "b38f959b-7865-31ac-8841-b88355519e10"
        },
        {
          "type": "guid",
          "guid": "e072b79c-4fa1-3a55-bdcd-4d7d9734d79b"
        }
      ],
      "premium": false,
      "links": {
        "web": {
          "href": "http://www.espn.com/mlb/recap?gameId=401695756"
        },
        "mobile": {
          "href": "http://m.espn.go.com/mlb/story?storyId=45398958"
        },
        "api": {
          "self": {
            "href": "https://content.core.api.espn.com/v1/sports/news/45398958"
          }
        },
        "app": {
          "sportscenter": {
            "href": "sportscenter://x-callback-url/showStory?uid=45398958"
          }
        }
      }
    },
    {
      "id": 45398905,
      "nowId": "1-45398905",
      "contentKey": "45398905-1-293-1",
      "dataSourceIdentifier": "6df7eed481ad0",
      "type": "Media",
      "headline": "Matt Chapman doubles Giants' lead with 10th HR of season",
      "description": "Matt Chapman sends one 420 feet to give the Giants a 2-0 lead over the Marlins.",
      "lastModified": "2025-05-31T01:58:58+00:00",
      "published": "2025-05-31T01:56:23+00:00",
      "images": [
        {
          "name": "Matt Chapman doubles Giants' lead with 10th HR of season",
          "height": 324,
          "width": 576,
          "url": "https://a.espncdn.com/media/motion/2025/0530/ss_20250530_215634337_2870764/ss_20250530_215634337_2870764.jpg",
          "caption": "Matt Chapman sends one 420 feet to give the Giants a 2-0 lead over the Marlins.",
          "alt": ""
        }
      ],
      "categories": [
        {
          "type": "athlete",
          "guid": "2eb5e599-5517-7cf4-8f12-de7e6bd899f3",
          "id": 164173,
          "description": "Matt Chapman",
          "sportId": 10,
          "uid": "s:1~l:10~a:33857",
          "athleteId": 33857,
          "athlete": {
            "id": 33857,
            "description": "Matt Chapman",
            "links": {
              "web": {
                "athletes": {
                  "href": "https://www.espn.com/mlb/player/_/id/33857"
                }
              },
              "mobile": {
                "athletes": {
                  "href": "https://www.espn.com/mlb/player/_/id/33857"
                }
              }
            }
          }
        },
        {
          "type": "team",
          "guid": "74909d10-eacb-1376-ef1e-d0f37d7c67ca",
          "id": 501,
          "description": "Miami Marlins",
          "sportId": 10,
          "uid": "s:1~l:10~t:28",
          "teamId": 28,
          "team": {
            "id": 28,
            "description": "Miami Marlins",
            "links": {
              "web": {
                "teams": {
                  "href": "https://www.espn.com/mlb/team/_/name/mia/miami-marlins"
                }
              },
              "mobile": {
                "teams": {
                  "href": "https://www.espn.com/mlb/team/_/name/mia/miami-marlins"
                }
              }
            }
          }
        },
        {
          "type": "league",
          "guid": "b38f959b-7865-31ac-8841-b88355519e10",
          "id": 80311,
          "description": "MLB",
          "sportId": 10,
          "uid": "s:1~l:10",
          "leagueId": 10,
          "league": {
            "id": 10,
            "description": "MLB",
            "abbreviation": "MLB",
            "links": {
              "web": {
                "leagues": {
                  "href": "https://www.espn.com/mlb/"
                }
              },
              "mobile": {
                "leagues": {
                  "href": "https://www.espn.com/mlb/"
                }
              }
            }
          }
        },
        {
          "type": "league",
          "guid": "486b53e9-9924-4652-82e3-1542a5849276",
          "id": 12023,
          "description": "Fantasy MLB",
          "sportId": 0,
          "leagueId": 3070,
          "league": {
            "id": 3070,
            "description": "Fantasy MLB",
            "links": {
              "web": {},
              "mobile": {}
            }
          }
        },
        {
          "type": "team",
          "guid": "e072b79c-4fa1-3a55-bdcd-4d7d9734d79b",
          "id": 751,
          "description": "San Francisco Giants",
          "sportId": 10,
          "uid": "s:1~l:10~t:26",
          "teamId": 26,
          "team": {
            "id": 26,
            "description": "San Francisco Giants",
            "links": {
              "web": {
                "teams": {
                  "href": "https://www.espn.com/mlb/team/_/name/sf/san-francisco-giants"
                }
              },
              "mobile": {
                "teams": {
                  "href": "https://www.espn.com/mlb/team/_/name/sf/san-francisco-giants"
                }
              }
            }
          }
        },
        {
          "type": "editorialindicator",
          "guid": "b14f9e1f-2d2c-3b10-b39d-d781f4c4aba7",
          "id": 711828,
          "description": "4 Star Rating"
        },
        {
          "type": "guid",
          "guid": "3bbbdbc9-bc88-3d07-849d-37f0acdab0e7"
        },
        {
          "type": "guid",
          "guid": "2eb5e599-5517-7cf4-8f12-de7e6bd899f3"
        },
        {
          "type": "guid",
          "guid": "74909d10-eacb-1376-ef1e-d0f37d7c67ca"
        },
        {
          "type": "guid",
          "guid": "b38f959b-7865-31ac-8841-b88355519e10"
        },
        {
          "type": "guid",
          "guid": "486b53e9-9924-4652-82e3-1542a5849276"
        },
        {
          "type": "guid",
          "guid": "e072b79c-4fa1-3a55-bdcd-4d7d9734d79b"
        },
        {
          "type": "guid",
          "guid": "b14f9e1f-2d2c-3b10-b39d-d781f4c4aba7"
        }
      ],
      "premium": false,
      "links": {
        "sportscenter": {
          "href": "sportscenter://x-callback-url/showVideo?videoID=45398905&videoDSI=6df7eed481ad0"
        },
        "web": {
          "self": {
            "href": "https://www.espn.com/video/clip?id=45398905",
            "dsi": {
              "href": "https://www.espn.com/video/clip?id=6df7eed481ad0"
            }
          },
          "seo": {
            "href": "https://www.espn.com/video/clip/_/id/45398905"
          },
          "href": "https://www.espn.com/video/clip?id=45398905"
        },
        "api": {
          "artwork": {
            "href": "https://artwork.api.espn.com/artwork/collections/media/8d42704f-860e-435e-a4ce-a95e838b122b"
          },
          "self": {
            "href": "https://content.core.api.espn.com/v1/video/clips/45398905"
          }
        }
      }
    },
    {
      "id": 45398771,
      "nowId": "1-45398771",
      "contentKey": "45398771-1-293-1",
      "dataSourceIdentifier": "b8ff867560702",
      "type": "Media",
      "headline": "Colorado Rockies vs. New York Mets: Game Highlights",
      "description": "Colorado Rockies vs. New York Mets: Game Highlights",
      "lastModified": "2025-05-31T01:50:51+00:00",
      "published": "2025-05-31T01:45:17+00:00",
      "images": [
        {
          "name": "Colorado Rockies vs. New York Mets: Game Highlights",
          "height": 324,
          "width": 576,
          "url": "https://a.espncdn.com/media/motion/wsc/2025/0531/e9f252ce-e739-43da-aa74-521010519362/e9f252ce-e739-43da-aa74-521010519362.jpg",
          "caption": "Colorado Rockies vs. New York Mets: Game Highlights",
          "alt": ""
        }
      ],
      "categories": [
        {
          "type": "athlete",
          "guid": "0b475684-88fe-1836-22a1-41a2e09d98a0",
          "id": 164438,
          "description": "Thairo Estrada",
          "sportId": 10,
          "uid": "s:1~l:10~a:36485",
          "athleteId": 36485,
          "athlete": {
            "id": 36485,
            "description": "Thairo Estrada",
            "links": {
              "web": {
                "athletes": {
                  "href": "https://www.espn.com/mlb/player/_/id/36485"
                }
              },
              "mobile": {
                "athletes": {
                  "href": "https://www.espn.com/mlb/player/_/id/36485"
                }
              }
            }
          }
        },
        {
          "type": "league",
          "guid": "b38f959b-7865-31ac-8841-b88355519e10",
          "id": 80311,
          "description": "MLB",
          "sportId": 10,
          "uid": "s:1~l:10",
          "leagueId": 10,
          "league": {
            "id": 10,
            "description": "MLB",
            "abbreviation": "MLB",
            "links": {
              "web": {
                "leagues": {
                  "href": "https://www.espn.com/mlb/"
                }
              },
              "mobile": {
                "leagues": {
                  "href": "https://www.espn.com/mlb/"
                }
              }
            }
          }
        },
        {
          "type": "athlete",
          "guid": "94848feb-9141-9679-d2cd-ae79905d969c",
          "id": 102243,
          "description": "Francisco Lindor",
          "sportId": 10,
          "uid": "s:1~l:10~a:32129",
          "athleteId": 32129,
          "athlete": {
            "id": 32129,
            "description": "Francisco Lindor",
            "links": {
              "web": {
                "athletes": {
                  "href": "https://www.espn.com/mlb/player/_/id/32129"
                }
              },
              "mobile": {
                "athletes": {
                  "href": "https://www.espn.com/mlb/player/_/id/32129"
                }
              }
            }
          }
        },
        {
          "type": "editorialindicator",
          "guid": "b14f9e1f-2d2c-3b10-b39d-d781f4c4aba7",
          "id": 711828,
          "description": "4 Star Rating"
        },
        {
          "type": "team",
          "guid": "f3f1ba71-05f1-a49a-0363-3b1d8e0db4cf",
          "id": 778,
          "description": "Colorado Rockies",
          "sportId": 10,
          "uid": "s:1~l:10~t:27",
          "teamId": 27,
          "team": {
            "id": 27,
            "description": "Colorado Rockies",
            "links": {
              "web": {
                "teams": {
                  "href": "https://www.espn.com/mlb/team/_/name/col/colorado-rockies"
                }
              },
              "mobile": {
                "teams": {
                  "href": "https://www.espn.com/mlb/team/_/name/col/colorado-rockies"
                }
              }
            }
          }
        },
        {
          "type": "team",
          "guid": "d08426cc-bf13-5d7b-5217-6d4662019bc6",
          "id": 449,
          "description": "New York Mets",
          "sportId": 10,
          "uid": "s:1~l:10~t:21",
          "teamId": 21,
          "team": {
            "id": 21,
            "description": "New York Mets",
            "links": {
              "web": {
                "teams": {
                  "href": "https://www.espn.com/mlb/team/_/name/nym/new-york-mets"
                }
              },
              "mobile": {
                "teams": {
                  "href": "https://www.espn.com/mlb/team/_/name/nym/new-york-mets"
                }
              }
            }
          }
        },
        {
          "type": "league",
          "guid": "486b53e9-9924-4652-82e3-1542a5849276",
          "id": 12023,
          "description": "Fantasy MLB",
          "sportId": 0,
          "leagueId": 3070,
          "league": {
            "id": 3070,
            "description": "Fantasy MLB",
            "links": {
              "web": {},
              "mobile": {}
            }
          }
        },
        {
          "type": "athlete",
          "guid": "f1684193-af1f-8abe-d820-f4c03ec794d0",
          "id": 73396,
          "description": "Starling Marte",
          "sportId": 10,
          "uid": "s:1~l:10~a:30830",
          "athleteId": 30830,
          "athlete": {
            "id": 30830,
            "description": "Starling Marte",
            "links": {
              "web": {
                "athletes": {
                  "href": "https://www.espn.com/mlb/player/_/id/30830"
                }
              },
              "mobile": {
                "athletes": {
                  "href": "https://www.espn.com/mlb/player/_/id/30830"
                }
              }
            }
          }
        },
        {
          "type": "editorialindicator",
          "guid": "d348c764-47d9-3e31-bd75-d39dfde52c26",
          "id": 711824,
          "description": "SC4U  - Eligible"
        },
        {
          "type": "editorialindicator",
          "guid": "f3e05446-8d07-3064-a239-c10c32884ea2",
          "id": 711821,
          "description": "SC4U - Full Highlight"
        },
        {
          "type": "guid",
          "guid": "0b475684-88fe-1836-22a1-41a2e09d98a0"
        },
        {
          "type": "guid",
          "guid": "b38f959b-7865-31ac-8841-b88355519e10"
        },
        {
          "type": "guid",
          "guid": "94848feb-9141-9679-d2cd-ae79905d969c"
        },
        {
          "type": "guid",
          "guid": "b14f9e1f-2d2c-3b10-b39d-d781f4c4aba7"
        },
        {
          "type": "guid",
          "guid": "f3f1ba71-05f1-a49a-0363-3b1d8e0db4cf"
        },
        {
          "type": "guid",
          "guid": "d08426cc-bf13-5d7b-5217-6d4662019bc6"
        },
        {
          "type": "guid",
          "guid": "486b53e9-9924-4652-82e3-1542a5849276"
        },
        {
          "type": "guid",
          "guid": "f1684193-af1f-8abe-d820-f4c03ec794d0"
        },
        {
          "type": "guid",
          "guid": "d348c764-47d9-3e31-bd75-d39dfde52c26"
        },
        {
          "type": "guid",
          "guid": "f3e05446-8d07-3064-a239-c10c32884ea2"
        },
        {
          "type": "guid",
          "guid": "36d6cdb8-297f-3f99-8e36-241f451aa127"
        }
      ],
      "premium": false,
      "links": {
        "sportscenter": {
          "href": "sportscenter://x-callback-url/showVideo?videoID=45398771&videoDSI=b8ff867560702"
        },
        "web": {
          "self": {
            "href": "https://www.espn.com/video/clip?id=45398771",
            "dsi": {
              "href": "https://www.espn.com/video/clip?id=b8ff867560702"
            }
          },
          "seo": {
            "href": "https://www.espn.com/video/clip/_/id/45398771"
          },
          "href": "https://www.espn.com/video/clip?id=45398771"
        },
        "api": {
          "artwork": {
            "href": "https://artwork.api.espn.com/artwork/collections/media/d86f794f-81ae-48a3-86cd-6d6429ec6fe0"
          },
          "self": {
            "href": "https://content.core.api.espn.com/v1/video/clips/45398771"
          }
        }
      }
    },
    {
      "id": 45398769,
      "nowId": "1-45398769",
      "contentKey": "45398769-1-21-1",
      "dataSourceIdentifier": "2b9dd41946178",
      "type": "Recap",
      "headline": "Lindor homers from both sides and Soto snaps hitless streak as Mets top Rockies 4-2",
      "description": "\u2014 Francisco Lindor homered from both sides of the plate and made a leaping catch at shortstop that saved at least two runs, sending the New York Mets to a 4-2 victory Friday night over the woeful Colorado Rockies.",
      "lastModified": "2025-05-31T01:44:56+00:00",
      "published": "2025-05-31T01:44:57+00:00",
      "images": [
        {
          "type": "stitcher",
          "name": "espn.applewatch.awayhome.1",
          "url": "https://s.espncdn.com/stitcher/sports/baseball/mlb/events/401695753.png?templateId=espn.applewatch.awayhome.1"
        },
        {
          "type": "stitcher",
          "name": "espn.applewatch.homeaway.1",
          "url": "https://s.espncdn.com/stitcher/sports/baseball/mlb/events/401695753.png?templateId=espn.applewatch.homeaway.1"
        },
        {
          "ratio": "16x9",
          "type": "stitcher",
          "name": "espn.all.awayhome.16x9.1",
          "height": 173,
          "width": 308,
          "url": "https://s.espncdn.com/stitcher/sports/baseball/mlb/events/401695753.png?templateId=espn.all.awayhome.16x9.1"
        },
        {
          "ratio": "16x9",
          "type": "stitcher",
          "name": "espn.all.homeaway.16x9.1",
          "height": 173,
          "width": 308,
          "url": "https://s.espncdn.com/stitcher/sports/baseball/mlb/events/401695753.png?templateId=espn.all.homeaway.16x9.1"
        },
        {
          "ratio": "1x1",
          "type": "stitcher",
          "name": "espn.all.awayhome.1x1.1",
          "height": 308,
          "width": 308,
          "url": "https://s.espncdn.com/stitcher/sports/baseball/mlb/events/401695753.png?templateId=espn.all.awayhome.1x1.1"
        },
        {
          "ratio": "1x1",
          "type": "stitcher",
          "name": "espn.all.homeaway.1x1.1",
          "height": 308,
          "width": 308,
          "url": "https://s.espncdn.com/stitcher/sports/baseball/mlb/events/401695753.png?templateId=espn.all.homeaway.1x1.1"
        },
        {
          "ratio": "5x2",
          "type": "stitcher",
          "name": "espn.all.awayhome.5x2.1",
          "height": 124,
          "width": 308,
          "url": "https://s.espncdn.com/stitcher/sports/baseball/mlb/events/401695753.png?templateId=espn.all.awayhome.5x2.1"
        },
        {
          "ratio": "5x2",
          "type": "stitcher",
          "name": "espn.all.homeaway.5x2.1",
          "height": 124,
          "width": 308,
          "url": "https://s.espncdn.com/stitcher/sports/baseball/mlb/events/401695753.png?templateId=espn.all.homeaway.5x2.1"
        },
        {
          "ratio": "16x9",
          "type": "stitcher",
          "name": "espn.all.awayhome.16x9.2",
          "height": 353,
          "width": 628,
          "url": "https://s.espncdn.com/stitcher/sports/baseball/mlb/events/401695753.png?templateId=espn.all.awayhome.16x9.2"
        },
        {
          "ratio": "16x9",
          "type": "stitcher",
          "name": "espn.all.homeaway.16x9.2",
          "height": 353,
          "width": 628,
          "url": "https://s.espncdn.com/stitcher/sports/baseball/mlb/events/401695753.png?templateId=espn.all.homeaway.16x9.2"
        },
        {
          "ratio": "5x2",
          "type": "stitcher",
          "name": "espn.all.awayhome.5x2.2",
          "height": 251,
          "width": 628,
          "url": "https://s.espncdn.com/stitcher/sports/baseball/mlb/events/401695753.png?templateId=espn.all.awayhome.5x2.2"
        },
        {
          "ratio": "5x2",
          "type": "stitcher",
          "name": "espn.all.homeaway.5x2.2",
          "height": 251,
          "width": 628,
          "url": "https://s.espncdn.com/stitcher/sports/baseball/mlb/events/401695753.png?templateId=espn.all.homeaway.5x2.2"
        },
        {
          "type": "Media",
          "name": "Colorado Rockies vs. New York Mets: Game Highlights",
          "height": 324,
          "width": 576,
          "url": "https://a.espncdn.com/media/motion/wsc/2025/0531/e9f252ce-e739-43da-aa74-521010519362/e9f252ce-e739-43da-aa74-521010519362.jpg",
          "caption": "Colorado Rockies vs. New York Mets: Game Highlights"
        }
      ],
      "categories": [
        {
          "type": "team",
          "guid": "f3f1ba71-05f1-a49a-0363-3b1d8e0db4cf",
          "id": 778,
          "description": "Colorado Rockies",
          "sportId": 10,
          "uid": "s:1~l:10~t:27",
          "teamId": 27,
          "team": {
            "id": 27,
            "description": "Colorado Rockies",
            "links": {
              "web": {
                "teams": {
                  "href": "https://www.espn.com/mlb/team/_/name/col/colorado-rockies"
                }
              },
              "mobile": {
                "teams": {
                  "href": "https://www.espn.com/mlb/team/_/name/col/colorado-rockies"
                }
              }
            }
          }
        },
        {
          "type": "team",
          "guid": "d08426cc-bf13-5d7b-5217-6d4662019bc6",
          "id": 449,
          "description": "New York Mets",
          "sportId": 10,
          "uid": "s:1~l:10~t:21",
          "teamId": 21,
          "team": {
            "id": 21,
            "description": "New York Mets",
            "links": {
              "web": {
                "teams": {
                  "href": "https://www.espn.com/mlb/team/_/name/nym/new-york-mets"
                }
              },
              "mobile": {
                "teams": {
                  "href": "https://www.espn.com/mlb/team/_/name/nym/new-york-mets"
                }
              }
            }
          }
        },
        {
          "type": "league",
          "guid": "b38f959b-7865-31ac-8841-b88355519e10",
          "id": 80311,
          "description": "MLB",
          "sportId": 10,
          "uid": "s:1~l:10",
          "leagueId": 10,
          "league": {
            "id": 10,
            "description": "MLB",
            "abbreviation": "MLB",
            "links": {
              "web": {
                "leagues": {
                  "href": "https://www.espn.com/mlb/"
                }
              },
              "mobile": {
                "leagues": {
                  "href": "https://www.espn.com/mlb/"
                }
              }
            }
          }
        },
        {
          "type": "guid",
          "guid": "f3f1ba71-05f1-a49a-0363-3b1d8e0db4cf"
        },
        {
          "type": "guid",
          "guid": "d08426cc-bf13-5d7b-5217-6d4662019bc6"
        },
        {
          "type": "guid",
          "guid": "b38f959b-7865-31ac-8841-b88355519e10"
        },
        {
          "type": "guid",
          "guid": "36d6cdb8-297f-3f99-8e36-241f451aa127"
        }
      ],
      "premium": false,
      "links": {
        "web": {
          "href": "http://www.espn.com/mlb/recap?gameId=401695753"
        },
        "mobile": {
          "href": "http://m.espn.go.com/mlb/story?storyId=45398769"
        },
        "api": {
          "self": {
            "href": "https://content.core.api.espn.com/v1/sports/news/45398769"
          }
        },
        "app": {
          "sportscenter": {
            "href": "sportscenter://x-callback-url/showStory?uid=45398769"
          }
        }
      }
    },
    {
      "id": 45398655,
      "nowId": "1-45398655",
      "contentKey": "45398655-1-21-1",
      "dataSourceIdentifier": "adb5c308a4039",
      "type": "Recap",
      "headline": "Christian Yelich homers twice, drives in 4 runs as Brewers beat NL-leading Phillies 6-2",
      "description": "\u2014 Christian Yelich hit two homers and drove in four runs, and Milwaukee limited National League-leading Philadelphia to four hits as the Brewers beat the Phillies 6-2 on Friday night for their fifth straight win.",
      "lastModified": "2025-05-31T01:36:56+00:00",
      "published": "2025-05-31T01:36:57+00:00",
      "images": [
        {
          "type": "stitcher",
          "name": "espn.applewatch.awayhome.1",
          "url": "https://s.espncdn.com/stitcher/sports/baseball/mlb/events/401695754.png?templateId=espn.applewatch.awayhome.1"
        },
        {
          "type": "stitcher",
          "name": "espn.applewatch.homeaway.1",
          "url": "https://s.espncdn.com/stitcher/sports/baseball/mlb/events/401695754.png?templateId=espn.applewatch.homeaway.1"
        },
        {
          "ratio": "16x9",
          "type": "stitcher",
          "name": "espn.all.awayhome.16x9.1",
          "height": 173,
          "width": 308,
          "url": "https://s.espncdn.com/stitcher/sports/baseball/mlb/events/401695754.png?templateId=espn.all.awayhome.16x9.1"
        },
        {
          "ratio": "16x9",
          "type": "stitcher",
          "name": "espn.all.homeaway.16x9.1",
          "height": 173,
          "width": 308,
          "url": "https://s.espncdn.com/stitcher/sports/baseball/mlb/events/401695754.png?templateId=espn.all.homeaway.16x9.1"
        },
        {
          "ratio": "1x1",
          "type": "stitcher",
          "name": "espn.all.awayhome.1x1.1",
          "height": 308,
          "width": 308,
          "url": "https://s.espncdn.com/stitcher/sports/baseball/mlb/events/401695754.png?templateId=espn.all.awayhome.1x1.1"
        },
        {
          "ratio": "1x1",
          "type": "stitcher",
          "name": "espn.all.homeaway.1x1.1",
          "height": 308,
          "width": 308,
          "url": "https://s.espncdn.com/stitcher/sports/baseball/mlb/events/401695754.png?templateId=espn.all.homeaway.1x1.1"
        },
        {
          "ratio": "5x2",
          "type": "stitcher",
          "name": "espn.all.awayhome.5x2.1",
          "height": 124,
          "width": 308,
          "url": "https://s.espncdn.com/stitcher/sports/baseball/mlb/events/401695754.png?templateId=espn.all.awayhome.5x2.1"
        },
        {
          "ratio": "5x2",
          "type": "stitcher",
          "name": "espn.all.homeaway.5x2.1",
          "height": 124,
          "width": 308,
          "url": "https://s.espncdn.com/stitcher/sports/baseball/mlb/events/401695754.png?templateId=espn.all.homeaway.5x2.1"
        },
        {
          "ratio": "16x9",
          "type": "stitcher",
          "name": "espn.all.awayhome.16x9.2",
          "height": 353,
          "width": 628,
          "url": "https://s.espncdn.com/stitcher/sports/baseball/mlb/events/401695754.png?templateId=espn.all.awayhome.16x9.2"
        },
        {
          "ratio": "16x9",
          "type": "stitcher",
          "name": "espn.all.homeaway.16x9.2",
          "height": 353,
          "width": 628,
          "url": "https://s.espncdn.com/stitcher/sports/baseball/mlb/events/401695754.png?templateId=espn.all.homeaway.16x9.2"
        },
        {
          "ratio": "5x2",
          "type": "stitcher",
          "name": "espn.all.awayhome.5x2.2",
          "height": 251,
          "width": 628,
          "url": "https://s.espncdn.com/stitcher/sports/baseball/mlb/events/401695754.png?templateId=espn.all.awayhome.5x2.2"
        },
        {
          "ratio": "5x2",
          "type": "stitcher",
          "name": "espn.all.homeaway.5x2.2",
          "height": 251,
          "width": 628,
          "url": "https://s.espncdn.com/stitcher/sports/baseball/mlb/events/401695754.png?templateId=espn.all.homeaway.5x2.2"
        },
        {
          "type": "Media",
          "name": "Milwaukee Brewers vs. Philadelphia Phillies: Game Highlights",
          "height": 324,
          "width": 576,
          "url": "https://a.espncdn.com/media/motion/wsc/2025/0531/404e1991-4231-4f90-a8c4-e7f375b74ee5/404e1991-4231-4f90-a8c4-e7f375b74ee5.jpg",
          "caption": "Milwaukee Brewers vs. Philadelphia Phillies: Game Highlights"
        }
      ],
      "categories": [
        {
          "type": "team",
          "guid": "ff1e263a-f6a6-93c3-1373-418623652ff0",
          "id": 474,
          "description": "Philadelphia Phillies",
          "sportId": 10,
          "uid": "s:1~l:10~t:22",
          "teamId": 22,
          "team": {
            "id": 22,
            "description": "Philadelphia Phillies",
            "links": {
              "web": {
                "teams": {
                  "href": "https://www.espn.com/mlb/team/_/name/phi/philadelphia-phillies"
                }
              },
              "mobile": {
                "teams": {
                  "href": "https://www.espn.com/mlb/team/_/name/phi/philadelphia-phillies"
                }
              }
            }
          }
        },
        {
          "type": "team",
          "guid": "4750d73d-d92e-b390-758c-2c7b44a810db",
          "id": 527,
          "description": "Milwaukee Brewers",
          "sportId": 10,
          "uid": "s:1~l:10~t:8",
          "teamId": 8,
          "team": {
            "id": 8,
            "description": "Milwaukee Brewers",
            "links": {
              "web": {
                "teams": {
                  "href": "https://www.espn.com/mlb/team/_/name/mil/milwaukee-brewers"
                }
              },
              "mobile": {
                "teams": {
                  "href": "https://www.espn.com/mlb/team/_/name/mil/milwaukee-brewers"
                }
              }
            }
          }
        },
        {
          "type": "league",
          "guid": "b38f959b-7865-31ac-8841-b88355519e10",
          "id": 80311,
          "description": "MLB",
          "sportId": 10,
          "uid": "s:1~l:10",
          "leagueId": 10,
          "league": {
            "id": 10,
            "description": "MLB",
            "abbreviation": "MLB",
            "links": {
              "web": {
                "leagues": {
                  "href": "https://www.espn.com/mlb/"
                }
              },
              "mobile": {
                "leagues": {
                  "href": "https://www.espn.com/mlb/"
                }
              }
            }
          }
        },
        {
          "type": "guid",
          "guid": "94ecf0c7-9bb1-3840-b51b-6ba50fa00c37"
        },
        {
          "type": "guid",
          "guid": "ff1e263a-f6a6-93c3-1373-418623652ff0"
        },
        {
          "type": "guid",
          "guid": "4750d73d-d92e-b390-758c-2c7b44a810db"
        },
        {
          "type": "guid",
          "guid": "b38f959b-7865-31ac-8841-b88355519e10"
        }
      ],
      "premium": false,
      "links": {
        "web": {
          "href": "http://www.espn.com/mlb/recap?gameId=401695754"
        },
        "mobile": {
          "href": "http://m.espn.go.com/mlb/story?storyId=45398655"
        },
        "api": {
          "self": {
            "href": "https://content.core.api.espn.com/v1/sports/news/45398655"
          }
        },
        "app": {
          "sportscenter": {
            "href": "sportscenter://x-callback-url/showStory?uid=45398655"
          }
        }
      }
    }
  ],
  "link": {
    "href": "https://www.espn.com/mlb/",
    "language": "en",
    "rel": [
      "index",
      "desktop",
      "league"
    ],
    "text": "All MLB News",
    "shortText": "All News",
    "isExternal": false,
    "isPremium": false
  }
}