{
  "$ref": "http://sports.core.api.espn.com/v2/sports/hockey/leagues/nhl/athletes/3024816?lang=en&region=us",
  "id": "3024816",
  "uid": "s:70~l:90~a:3024816",
  "guid": "ffb74b25-e735-bce8-df8d-0b456d1b5143",
  "type": "hockey",
  "alternateIds": {
    "sdr": "3024816"
  },
  "alternateId": "3024816",
  "firstName": "Austin",
  "lastName": "Czarnik",
  "fullName": "Austin Czarnik",
  "displayName": "Austin Czarnik",
  "shortName": "A. Czarnik",
  "weight": 175.0,
  "displayWeight": "175 lbs",
  "height": 69.0,
  "displayHeight": "5' 9\"",
  "age": 32,
  "dateOfBirth": "1992-12-12T08:00Z",
  "debutYear": 2016,
  "links": [
    {
      "language": "en-US",
      "rel": [
        "playercard",
        "desktop",
        "athlete"
      ],
      "href": "https://www.espn.com/nhl/player/_/id/3024816",
      "text": "Player Card",
      "shortText": "Player Card",
      "isExternal": false,
      "isPremium": false
    },
    {
      "language": "en-US",
      "rel": [
        "stats",
        "desktop",
        "athlete"
      ],
      "href": "https://www.espn.com/nhl/player/stats/_/id/3024816/austin-czarnik",
      "text": "Stats",
      "shortText": "Stats",
      "isExternal": false,
      "isPremium": false
    },
    {
      "language": "en-US",
      "rel": [
        "splits",
        "desktop",
        "athlete"
      ],
      "href": "https://www.espn.com/nhl/player/splits/_/id/3024816/austin-czarnik",
      "text": "Splits",
      "shortText": "Splits",
      "isExternal": false,
      "isPremium": false
    },
    {
      "language": "en-US",
      "rel": [
        "gamelog",
        "desktop",
        "athlete"
      ],
      "href": "https://www.espn.com/nhl/player/gamelog/_/id/3024816/austin-czarnik",
      "text": "Game Log",
      "shortText": "Game Log",
      "isExternal": false,
      "isPremium": false
    },
    {
      "language": "en-US",
      "rel": [
        "news",
        "desktop",
        "athlete"
      ],
      "href": "https://www.espn.com/nhl/player/news/_/id/3024816/austin-czarnik",
      "text": "News",
      "shortText": "News",
      "isExternal": false,
      "isPremium": false
    },
    {
      "language": "en-US",
      "rel": [
        "bio",
        "desktop",
        "athlete"
      ],
      "href": "https://www.espn.com/nhl/player/bio/_/id/3024816/austin-czarnik",
      "text": "Bio",
      "shortText": "Bio",
      "isExternal": false,
      "isPremium": false
    },
    {
      "language": "en-US",
      "rel": [
        "overview",
        "desktop",
        "athlete"
      ],
      "href": "https://www.espn.com/nhl/player/_/id/3024816/austin-czarnik",
      "text": "Overview",
      "shortText": "Overview",
      "isExternal": false,
      "isPremium": false
    }
  ],
  "birthPlace": {
    "city": "Washington",
    "state": "MI",
    "country": "USA"
  },
  "birthCountry": {
    "abbreviation": "USA"
  },
  "college": {
    "$ref": "http://sports.core.api.espn.com/v2/colleges/193?lang=en&region=us"
  },
  "slug": "austin-czarnik",
  "headshot": {
    "href": "https://a.espncdn.com/i/headshots/nhl/players/full/3024816.png",
    "alt": "Austin Czarnik"
  },
  "jersey": "21",
  "hand": {
    "type": "RIGHT",
    "abbreviation": "R",
    "displayValue": "Right"
  },
  "position": {
    "$ref": "http://sports.core.api.espn.com/v2/sports/hockey/leagues/nhl/positions/1?lang=en&region=us",
    "id": "1",
    "name": "Center",
    "displayName": "Center",
    "abbreviation": "C",
    "leaf": true,
    "parent": {
      "$ref": "http://sports.core.api.espn.com/v2/sports/hockey/leagues/nhl/positions/20?lang=en&region=us"
    }
  },
  "linked": true,
  "team": {
    "$ref": "http://sports.core.api.espn.com/v2/sports/hockey/leagues/nhl/seasons/2024/teams/5?lang=en&region=us"
  },
  "statistics": {
    "$ref": "http://sports.core.api.espn.com/v2/sports/hockey/leagues/nhl/athletes/3024816/statistics?lang=en&region=us"
  },
  "contracts": {
    "$ref": "http://sports.core.api.espn.com/v2/sports/hockey/leagues/nhl/athletes/3024816/contracts?lang=en&region=us"
  },
  "experience": {
    "years": 2
  },
  "active": false,
  "status": {
    "id": "4",
    "name": "Minors",
    "type": "minors",
    "abbreviation": "Minors"
  },
  "statisticslog": {
    "$ref": "http://sports.core.api.espn.com/v2/sports/hockey/leagues/nhl/athletes/3024816/statisticslog?lang=en&region=us"
  }
}